Metadata-Version: 1.0
Name: drawk
Version: 0.0.1
Summary: drak k .
Home-page: https://github.com/jungamer/drawk
Author: jungamer
Author-email: 624621566@qq.com
License: MIT
Platform: UNKNOWN
